README.rst
setup.py
charlotte_lite/__init__.py
charlotte_lite/charlotte_DB_SDK.py
charlotte_lite.egg-info/PKG-INFO
charlotte_lite.egg-info/SOURCES.txt
charlotte_lite.egg-info/dependency_links.txt
charlotte_lite.egg-info/top_level.txt