Metadata-Version: 1.1
Name: charlotte-lite
Version: 0.9.2
Summary: A lighting fast SDK for a lighting fast DB
Home-page: https://github.com/Danlobaton/flash-Charlotte-docs
Author: Daniel A. Lobaton
Author-email: dlobaton2@gmail.com
License: MIT
Keywords: SDK
Platform: UNKNOWN
Classifier: Development Status :: 4 - Beta
Classifier: Intended Audience :: Developers
Classifier: License :: OSI Approved :: MIT License
